snn_functions.cpython-39-i386-linux-gnu.so
ClustAssessPy-1.0.2.dist-info/top_level.txt
ClustAssessPy-1.0.2.dist-info/RECORD
ClustAssessPy-1.0.2.dist-info/LICENSE.txt
ClustAssessPy-1.0.2.dist-info/METADATA
ClustAssessPy-1.0.2.dist-info/WHEEL
ClustAssessPy/plotting_functions.py
ClustAssessPy/dim_reduction_assessment.py
ClustAssessPy/__init__.py
ClustAssessPy/_common_imports.py
ClustAssessPy/basic_functions.py
ClustAssessPy/graph_clustering_assessment.py
ClustAssessPy/graph_construction_assessment.py
ClustAssessPy/_private_helper_functions.py
ClustAssessPy.libs/libstdc++-d2a021ba.so.6.0.32
ClustAssessPy.libs/libgcc_s-f3fb5a36.so.1
