Metadata-Version: 2.1
Name: ClustAssessPy
Version: 1.0.2
Summary: Python package for systematic assessment of clustering results stability on single-cell data.
Author: Rafael Kollyfas
Author-email: rk720@cam.ac.uk
License: MIT
Keywords: clustering,stability,assessment,machine learning,graph,network,community,detection
Requires-Python: >=3.7
License-File: LICENSE.txt
Requires-Dist: numpy
Requires-Dist: pandas
Requires-Dist: scanpy
Requires-Dist: umap-learn
Requires-Dist: seaborn
Requires-Dist: matplotlib
Requires-Dist: scipy
Requires-Dist: networkx
Requires-Dist: plotnine
Requires-Dist: pynndescent
Requires-Dist: leidenalg
Requires-Dist: louvain
Requires-Dist: igraph
